{"is_source_file": true, "format": "Kotlin DSL (Gradle Kotlin Script)", "description": "This file is a Gradle build configuration script written in Kotlin DSL for an Android application module. It specifies plugins, Android build options, dependencies, and build features for the project.", "external_files": [], "external_methods": ["getDefaultProguardFile", "JavaVersion.VERSION_17"], "published": [], "classes": [], "methods": [{"name": "getDefaultProguardFile", "description": "Returns the default Proguard file for minification."}], "calls": ["getDefaultProguardFile", "JavaVersion.VERSION_17"], "search-terms": ["build.gradle.kts", "Gradle Kotlin DSL", "android application", "dependencies", "Android TV", "media3", "Kotlin Android", "buildFeatures", "compileSdk", "targetSdk"], "state": 2, "file_id": 13, "knowledge_revision": 31, "git_revision": "f85fb7dfad98bf59ff84b5f04c866c022a883570", "hash": "4c9cba2fcdc039c89467e157195a1a38", "format-version": 4, "code-base-name": "tetris_android_tv_frontend", "filename": "tetris_android_tv_frontend/app/build.gradle.kts", "revision_history": [{"31": "f85fb7dfad98bf59ff84b5f04c866c022a883570"}]}